Metadata-Version: 2.2
Name: foundrytools
Version: 0.1.4
Summary: A library for working with fonts in Python.
Home-page: https://github.com/ftCLI/FoundryTools
Author: ftCLI
Author-email: ftcli@proton.me
Classifier: Development Status :: 5 - Production/Stable
Classifier: Intended Audience :: Developers
Classifier: License :: OSI Approved :: MIT License
Classifier: Natural Language :: English
Classifier: Operating System :: OS Independent
Classifier: Programming Language :: Python :: 3
Classifier: Programming Language :: Python :: 3.9
Classifier: Programming Language :: Python :: 3.10
Classifier: Programming Language :: Python :: 3.11
Classifier: Programming Language :: Python :: 3.12
Classifier: Programming Language :: Python :: 3.13
Classifier: Topic :: Text Processing :: Fonts
Requires-Python: >=3.9
License-File: LICENSE
Requires-Dist: afdko>=4.0.2
Requires-Dist: cffsubr>=0.3.0
Requires-Dist: defcon>=0.12.1
Requires-Dist: dehinter>=4.0.0
Requires-Dist: fonttools[pathops,unicode,woff]>=4.56.0
Requires-Dist: setuptools>=76.1.0
Requires-Dist: ttfautohint-py>=0.5.1
Requires-Dist: ufo-extractor>=0.8.1
Requires-Dist: ufo2ft>=3.4.2
Dynamic: author
Dynamic: author-email
Dynamic: classifier
Dynamic: description
Dynamic: description-content-type
Dynamic: home-page
Dynamic: requires-dist
Dynamic: requires-python
Dynamic: summary
